README.md
setup.cfg
setup.py
Lnpay/__init__.py
Lnpay.egg-info/PKG-INFO
Lnpay.egg-info/SOURCES.txt
Lnpay.egg-info/dependency_links.txt
Lnpay.egg-info/requires.txt
Lnpay.egg-info/top_level.txt