Metadata-Version: 1.0
Name: Lnpay
Version: 1.0
Summary: Lnpay SDK
Home-page: https://github.com/Zenitsudeck/Lnpay
Author: Zenitsudeck
Author-email: UNKNOWN
License: UNKNOWN
Platform: UNKNOWN
